jmc/__init__.py
jmc/__main__.py
jmc/config.py
jmc/terminal_commands.py
jmc/api/__init__.py
jmc/api/_py_jmc.py
jmc/compile/__init__.py
jmc/compile/compiling.py
jmc/compile/datapack.py
jmc/compile/datapack_data.py
jmc/compile/decorator_parse.py
jmc/compile/exception.py
jmc/compile/expression_eval.py
jmc/compile/header.py
jmc/compile/header_parse.py
jmc/compile/lexer.py
jmc/compile/lexer_func_content.py
jmc/compile/log.py
jmc/compile/pack_version.py
jmc/compile/test_compile.py
jmc/compile/tokenizer.py
jmc/compile/utils.py
jmc/compile/vanilla_command.py
jmc/compile/command/__init__.py
jmc/compile/command/_flow_control.py
jmc/compile/command/condition.py
jmc/compile/command/flow_control.py
jmc/compile/command/jmc_function.py
jmc/compile/command/jmc_function_mixin.py
jmc/compile/command/nbt_operation.py
jmc/compile/command/utils.py
jmc/compile/command/var_operation.py
jmc/compile/command/builtin_function/__init__.py
jmc/compile/command/builtin_function/_var_operation.py
jmc/compile/command/builtin_function/bool_function.py
jmc/compile/command/builtin_function/execute_excluded.py
jmc/compile/command/builtin_function/jmc_command.py
jmc/compile/command/builtin_function/load_once.py
jmc/compile/command/builtin_function/load_only.py
jmc/compile/command/builtin_function/utils/__init__.py
jmc/compile/command/builtin_function/utils/isolated.py
jmc/terminal/__init__.py
jmc/terminal/configuration.py
jmc/terminal/main.py
jmc/terminal/utils.py
jmcfunction-1.2.19.dist-info/METADATA
jmcfunction-1.2.19.dist-info/WHEEL
jmcfunction-1.2.19.dist-info/entry_points.txt
jmcfunction-1.2.19.dist-info/top_level.txt
jmcfunction-1.2.19.dist-info/RECORD
