Metadata-Version: 2.4
Name: jmcfunction
Version: 1.2.19
Summary: Compiler for JMC (JavaScript-like Minecraft Function), a mcfunction extension language for making Minecraft Datapack.
Author: WingedSeal
Author-email: firm09719@gmail.com
License: MIT License
Project-URL: Documentation, https://jmc.wingedseal.com/
Project-URL: Repository, https://github.com/WingedSeal/jmc
Keywords: python,minecraft,mcfunction,datapack,compiler
Classifier: Development Status :: 5 - Production/Stable
Classifier: Intended Audience :: Developers
Classifier: Programming Language :: Python :: 3.12
Classifier: Programming Language :: Python :: 3.13
Classifier: Operating System :: Unix
Classifier: Operating System :: MacOS :: MacOS X
Classifier: Operating System :: Microsoft :: Windows
Requires-Python: >=3.12
Dynamic: author
Dynamic: author-email
Dynamic: classifier
Dynamic: description
Dynamic: description-content-type
Dynamic: keywords
Dynamic: license
Dynamic: project-url
Dynamic: requires-python
Dynamic: summary
